UIpygame/PyUI.py
UIpygame/__init__.py
uipygame-1.5.2.dist-info/METADATA
uipygame-1.5.2.dist-info/WHEEL
uipygame-1.5.2.dist-info/licenses/LICENSE
uipygame-1.5.2.dist-info/RECORD
