Metadata-Version: 2.4
Name: UIpygame
Version: 1.5.2
Summary: A gui module for pygame
Project-URL: Homepage, https://github.com/lazerwolfegod/PyUI
Project-URL: Bug Tracker, https://github.com/lazerwolfegod/PyUI/issues
Author-email: christianharris-3 <christianharris0403@gmail.com>
License-File: LICENSE
Classifier: License :: OSI Approved :: MIT License
Classifier: Operating System :: OS Independent
Classifier: Programming Language :: Python :: 3
Requires-Python: >=3.10
